mypackage/__init__.py
mypackage/cli.py
test_mypackage-0.1.1.dist-info/METADATA
test_mypackage-0.1.1.dist-info/WHEEL
test_mypackage-0.1.1.dist-info/entry_points.txt
test_mypackage-0.1.1.dist-info/top_level.txt
test_mypackage-0.1.1.dist-info/RECORD
