Metadata-Version: 2.1
Name: test-mypackage
Version: 0.1.1
Requires-Dist: numpy
Requires-Dist: pandas
Requires-Dist: matplotlib
